{
    "version": "2.1.451",
    "description": "Personalized Stats and Insights Powered by Billions of Matches",
    "homepage": "https://blitz.gg",
    "license": "Proprietary",
    "architecture": {
        "64bit": {
            "url": "https://blitz-main.blitz.gg/Blitz-2.1.451.exe#/dl.7z",
            "hash": "c7d9e491e8dcfd879423effa187f31a46615e05c225e2a9104f58391b7fc977e"
        }
    },
    "pre_install": "Expand-7zipArchive \"$dir\\`$PLUGINSDIR\\app-64.7z\" \"$dir\"",
    "post_install": "Remove-Item \"$dir\\`$PLUGINSDIR\", \"$dir\\`$R0\", \"$dir\\resources\\app-update.yml\" -Recurse -Force",
    "shortcuts": [
        [
            "Blitz.exe",
            "Blitz"
        ]
    ],
    "checkver": {
        "script": [
            "try {",
            "    $Response = Invoke-WebRequest -Uri 'https://blitz.gg/download/win' -MaximumRedirection 0",
            "} catch {",
            "    $_.Exception.Response.Headers.Location.OriginalString",
            "}"
        ],
        "regex": "([\\d.]+).exe"
    },
    "autoupdate": {
        "architecture": {
            "64bit": {
                "url": "https://blitz-main.blitz.gg/Blitz-$version.exe#/dl.7z"
            }
        }
    }
}
