{
    "version": "0.17.4",
    "description": "Anti-Detect Browser",
    "homepage": "https://donutbrowser.com",
    "license": "AGPL-3.0",
    "architecture": {
        "64bit": {
            "url": "https://github.com/zhom/donutbrowser/releases/download/v0.17.4/Donut_0.17.4_x64-setup.exe#/dl.7z",
            "hash": "0e837303bfb4d602e2278997fcf27305573790b58ab053335a7ccb3c0817b626"
        }
    },
    "post_install": "Remove-Item \"$dir\\`$PLUGINSDIR\" -Recurse -Force",
    "shortcuts": [
        [
            "donutbrowser.exe",
            "Donut"
        ]
    ],
    "post_uninstall": "Remove-Item \"$env:APPDATA\\Microsoft\\Windows\\Start Menu\\Programs\\Camoufox Private Browsing.lnk\" -ErrorAction SilentlyContinue",
    "checkver": {
        "github": "https://github.com/zhom/donutbrowser"
    },
    "autoupdate": {
        "architecture": {
            "64bit": {
                "url": "https://github.com/zhom/donutbrowser/releases/download/v$version/Donut_$version_x64-setup.exe#/dl.7z"
            }
        }
    }
}
